fueled/__init__.py
fueled/utils.py
fueled/data/vehicles.json
fueled-0.0.4.dist-info/METADATA
fueled-0.0.4.dist-info/WHEEL
fueled-0.0.4.dist-info/top_level.txt
fueled-0.0.4.dist-info/RECORD
