Metadata-Version: 2.1
Name: fueled
Version: 0.0.4
Summary: A Python package for vehicle mileage calculations
Home-page: https://github.com/shoshone-s/fueled
Author: shoshone-s
Classifier: Programming Language :: Python :: 3
Classifier: License :: OSI Approved :: MIT License
Classifier: Operating System :: OS Independent
Requires-Python: >=3.11.0
